strawberry_sqlalchemy_mapper/__init__.py
strawberry_sqlalchemy_mapper/exc.py
strawberry_sqlalchemy_mapper/loader.py
strawberry_sqlalchemy_mapper/mapper.py
strawberry_sqlalchemy_mapper/pydantic.py
strawberry_sqlalchemy_mapper/relay.py
strawberry_sqlalchemy_mapper/sqlakeyset/__init__.py
strawberry_sqlalchemy_mapper/sqlakeyset/columns.py
strawberry_sqlalchemy_mapper/sqlakeyset/paging.py
strawberry_sqlalchemy_mapper/sqlakeyset/results.py
strawberry_sqlalchemy_mapper/sqlakeyset/serial.py
aio_strawberry_sqlalchemy_mapper-0.8.1.dist-info/LICENSE.txt
aio_strawberry_sqlalchemy_mapper-0.8.1.dist-info/WHEEL
aio_strawberry_sqlalchemy_mapper-0.8.1.dist-info/METADATA
aio_strawberry_sqlalchemy_mapper-0.8.1.dist-info/RECORD
