Metadata-Version: 2.1
Name: aio-strawberry-sqlalchemy-mapper
Version: 0.8.1
Summary: Automatically generate fields for strawberry types from SQLAlchemy models.
Home-page: https://github.com/gazorby/strawberry-sqlalchemy-mapper
License: MIT
Keywords: graphql,sqlalchemy,pydantic,model
Author: Expedock Software, Inc
Author-email: rui@expedock.com
Maintainer: gazorby
Maintainer-email: gazorby@pm.me
Requires-Python: >=3.7,<4.0
Classifier: Development Status :: 4 - Beta
Classifier: License :: OSI Approved :: MIT License
Classifier: Programming Language :: Python :: 3
Classifier: Programming Language :: Python :: 3.7
Classifier: Programming Language :: Python :: 3.8
Classifier: Programming Language :: Python :: 3.9
Classifier: Programming Language :: Python :: 3.10
Classifier: Programming Language :: Python :: 3
Requires-Dist: SQLAlchemy[asyncio] (>=1.4.39,<2.0.0)
Requires-Dist: importlib-metadata (>=4.11.1)
Requires-Dist: pydantic (>=1.9.1)
Requires-Dist: sentinel (>=1.0.0,<2.0.0)
Requires-Dist: strawberry-graphql (>=0.95)
Project-URL: Documentation, https://github.com/gazorby/strawberry-sqlalchemy-mapper
Project-URL: Repository, https://github.com/gazorby/strawberry-sqlalchemy-mapper
